[
  {
    "ayat_id": 4847,
    "ayat_number": 1,
    "ayat_arabic": "اِقْتَرَبَتِ السَّاعَةُ وَانْشَقَّ الْقَمَرُ ",
    "ayat_bahasa": " Saat (hari Kiamat) semakin dekat, bulan pun terbelah. ",
    "ayat_sound": "https://quran.kemenag.go.id/cmsq/source/s01/054001.mp3",
    "surat_id": 54,
    "juz_id": 27,
    "page_number": 528
  },
  {
    "ayat_id": 4848,
    "ayat_number": 2,
    "ayat_arabic": "وَاِنْ يَّرَوْا اٰيَةً يُّعْرِضُوْا وَيَقُوْلُوْا سِحْرٌ مُّسْتَمِرٌّ",
    "ayat_bahasa": "Dan jika mereka (orang-orang musyrikin) melihat suatu tanda (mukjizat), mereka berpaling dan berkata, “(Ini adalah) sihir yang terus menerus.” ",
    "ayat_sound": "https://quran.kemenag.go.id/cmsq/source/s01/054002.mp3",
    "surat_id": 54,
    "juz_id": 27,
    "page_number": 528
  },
  {
    "ayat_id": 4849,
    "ayat_number": 3,
    "ayat_arabic": "وَكَذَّبُوْا وَاتَّبَعُوْٓا اَهْوَاۤءَهُمْ وَكُلُّ اَمْرٍ مُّسْتَقِرٌّ",
    "ayat_bahasa": "Dan mereka mendustakan (Muhammad) dan mengikuti keinginannya, padahal setiap urusan telah ada ketetapannya.",
    "ayat_sound": "https://quran.kemenag.go.id/cmsq/source/s01/054003.mp3",
    "surat_id": 54,
    "juz_id": 27,
    "page_number": 528
  },
  {
    "ayat_id": 4850,
    "ayat_number": 4,
    "ayat_arabic": "وَلَقَدْ جَاۤءَهُمْ مِّنَ الْاَنْبَاۤءِ مَا فِيْهِ مُزْدَجَرٌۙ  ",
    "ayat_bahasa": "Dan sungguh, telah datang kepada mereka beberapa kisah yang di dalamnya terdapat ancaman (terhadap kekafiran),",
    "ayat_sound": "https://quran.kemenag.go.id/cmsq/source/s01/054004.mp3",
    "surat_id": 54,
    "juz_id": 27,
    "page_number": 528
  },
  {
    "ayat_id": 4851,
    "ayat_number": 5,
    "ayat_arabic": "حِكْمَةٌ ۢ بَالِغَةٌ فَمَا تُغْنِ النُّذُرُۙ  ",
    "ayat_bahasa": "(itulah) suatu hikmah yang sempurna, tetapi peringatan-peringatan itu tidak berguna (bagi mereka),",
    "ayat_sound": "https://quran.kemenag.go.id/cmsq/source/s01/054005.mp3",
    "surat_id": 54,
    "juz_id": 27,
    "page_number": 528
  },
  {
    "ayat_id": 4852,
    "ayat_number": 6,
    "ayat_arabic": "فَتَوَلَّ عَنْهُمْ ۘ يَوْمَ يَدْعُ الدَّاعِ اِلٰى شَيْءٍ نُّكُرٍۙ  ",
    "ayat_bahasa": "maka berpalinglah engkau (Muhammad) dari mereka pada hari (ketika) penyeru (malaikat) mengajak (mereka) kepada sesuatu yang tidak menyenangkan (hari pembalasan), ",
    "ayat_sound": "https://quran.kemenag.go.id/cmsq/source/s01/054006.mp3",
    "surat_id": 54,
    "juz_id": 27,
    "page_number": 528
  },
  {
    "ayat_id": 4853,
    "ayat_number": 7,
    "ayat_arabic": "خُشَّعًا اَبْصَارُهُمْ يَخْرُجُوْنَ مِنَ الْاَجْدَاثِ كَاَنَّهُمْ جَرَادٌ مُّنْتَشِرٌۙ  ",
    "ayat_bahasa": "pandangan mereka tertunduk, ketika mereka keluar dari kuburan, seakan-akan mereka belalang yang beterbangan,",
    "ayat_sound": "https://quran.kemenag.go.id/cmsq/source/s01/054007.mp3",
    "surat_id": 54,
    "juz_id": 27,
    "page_number": 529
  },
  {
    "ayat_id": 4854,
    "ayat_number": 8,
    "ayat_arabic": "مُّهْطِعِيْنَ اِلَى الدَّاعِۗ يَقُوْلُ الْكٰفِرُوْنَ هٰذَا يَوْمٌ عَسِرٌ ",
    "ayat_bahasa": "dengan patuh mereka segera datang kepada penyeru itu. Orang-orang kafir berkata, “Ini adalah hari yang sulit.” ",
    "ayat_sound": "https://quran.kemenag.go.id/cmsq/source/s01/054008.mp3",
    "surat_id": 54,
    "juz_id": 27,
    "page_number": 529
  },
  {
    "ayat_id": 4855,
    "ayat_number": 9,
    "ayat_arabic": "۞ كَذَّبَتْ قَبْلَهُمْ قَوْمُ نُوْحٍ فَكَذَّبُوْا عَبْدَنَا وَقَالُوْا مَجْنُوْنٌ وَّازْدُجِرَ",
    "ayat_bahasa": "Sebelum mereka, kaum Nuh juga telah mendustakan (rasul), maka mereka mendustakan hamba Kami (Nuh) dan mengatakan, “Dia orang gila!” Lalu diusirnya dengan ancaman. ",
    "ayat_sound": "https://quran.kemenag.go.id/cmsq/source/s01/054009.mp3",
    "surat_id": 54,
    "juz_id": 27,
    "page_number": 529
  },
  {
    "ayat_id": 4856,
    "ayat_number": 10,
    "ayat_arabic": "فَدَعَا رَبَّهٗٓ اَنِّيْ مَغْلُوْبٌ فَانْتَصِرْ",
    "ayat_bahasa": "Maka dia (Nuh) mengadu kepada Tuhannya, “Sesungguhnya aku telah dikalahkan, maka tolonglah (aku).”",
    "ayat_sound": "https://quran.kemenag.go.id/cmsq/source/s01/054010.mp3",
    "surat_id": 54,
    "juz_id": 27,
    "page_number": 529
  },
  {
    "ayat_id": 4857,
    "ayat_number": 11,
    "ayat_arabic": "فَفَتَحْنَآ اَبْوَابَ السَّمَاۤءِ بِمَاۤءٍ مُّنْهَمِرٍۖ  ",
    "ayat_bahasa": "Lalu Kami bukakan pintu-pintu langit dengan (menurunkan) air yang tercurah,",
    "ayat_sound": "https://quran.kemenag.go.id/cmsq/source/s01/054011.mp3",
    "surat_id": 54,
    "juz_id": 27,
    "page_number": 529
  },
  {
    "ayat_id": 4858,
    "ayat_number": 12,
    "ayat_arabic": "وَّفَجَّرْنَا الْاَرْضَ عُيُوْنًا فَالْتَقَى الْمَاۤءُ عَلٰٓى اَمْرٍ قَدْ قُدِرَ ۚ",
    "ayat_bahasa": "dan Kami jadikan bumi menyemburkan mata-mata air maka bertemulah (air-air) itu sehingga (meluap menimbulkan) keadaan (bencana) yang telah ditetapkan. ",
    "ayat_sound": "https://quran.kemenag.go.id/cmsq/source/s01/054012.mp3",
    "surat_id": 54,
    "juz_id": 27,
    "page_number": 529
  },
  {
    "ayat_id": 4859,
    "ayat_number": 13,
    "ayat_arabic": "وَحَمَلْنٰهُ عَلٰى ذَاتِ اَلْوَاحٍ وَّدُسُرٍۙ  ",
    "ayat_bahasa": "Dan Kami angkut dia (Nuh) ke atas (kapal) yang terbuat dari papan dan pasak, ",
    "ayat_sound": "https://quran.kemenag.go.id/cmsq/source/s01/054013.mp3",
    "surat_id": 54,
    "juz_id": 27,
    "page_number": 529
  },
  {
    "ayat_id": 4860,
    "ayat_number": 14,
    "ayat_arabic": "تَجْرِيْ بِاَعْيُنِنَاۚ جَزَاۤءً لِّمَنْ كَانَ كُفِرَ ",
    "ayat_bahasa": "yang berlayar dengan pemeliharaan (pengawasan) Kami sebagai balasan bagi orang yang telah diingkari (kaumnya).",
    "ayat_sound": "https://quran.kemenag.go.id/cmsq/source/s01/054014.mp3",
    "surat_id": 54,
    "juz_id": 27,
    "page_number": 529
  },
  {
    "ayat_id": 4861,
    "ayat_number": 15,
    "ayat_arabic": "وَلَقَدْ تَّرَكْنٰهَآ اٰيَةً فَهَلْ مِنْ مُّدَّكِرٍ",
    "ayat_bahasa": "Dan sungguh, kapal itu telah Kami jadikan sebagai tanda (pelajaran). Maka adakah orang yang mau mengambil pelajaran?",
    "ayat_sound": "https://quran.kemenag.go.id/cmsq/source/s01/054015.mp3",
    "surat_id": 54,
    "juz_id": 27,
    "page_number": 529
  },
  {
    "ayat_id": 4862,
    "ayat_number": 16,
    "ayat_arabic": "فَكَيْفَ كَانَ عَذَابِيْ وَنُذُرِ ",
    "ayat_bahasa": "Maka betapa dahsyatnya azab-Ku dan peringatan-Ku! ",
    "ayat_sound": "https://quran.kemenag.go.id/cmsq/source/s01/054016.mp3",
    "surat_id": 54,
    "juz_id": 27,
    "page_number": 529
  },
  {
    "ayat_id": 4863,
    "ayat_number": 17,
    "ayat_arabic": "وَلَقَدْ يَسَّرْنَا الْقُرْاٰنَ لِلذِّكْرِ فَهَلْ مِنْ مُّدَّكِرٍ ",
    "ayat_bahasa": "Dan sungguh, telah Kami mudahkan Al-Qur'an untuk peringatan, maka adakah orang yang mau mengambil pelajaran?",
    "ayat_sound": "https://quran.kemenag.go.id/cmsq/source/s01/054017.mp3",
    "surat_id": 54,
    "juz_id": 27,
    "page_number": 529
  },
  {
    "ayat_id": 4864,
    "ayat_number": 18,
    "ayat_arabic": "كَذَّبَتْ عَادٌ فَكَيْفَ كَانَ عَذَابِيْ وَنُذُرِ ",
    "ayat_bahasa": "Kaum ‘Ad pun telah mendustakan. Maka betapa dahsyatnya azab-Ku dan peringatan-Ku! ",
    "ayat_sound": "https://quran.kemenag.go.id/cmsq/source/s01/054018.mp3",
    "surat_id": 54,
    "juz_id": 27,
    "page_number": 529
  },
  {
    "ayat_id": 4865,
    "ayat_number": 19,
    "ayat_arabic": "اِنَّآ اَرْسَلْنَا عَلَيْهِمْ رِيْحًا صَرْصَرًا فِيْ يَوْمِ نَحْسٍ مُّسْتَمِرٍّۙ  ",
    "ayat_bahasa": "Sesungguhnya Kami telah menghembuskan angin yang sangat kencang kepada mereka pada hari nahas yang terus menerus, ",
    "ayat_sound": "https://quran.kemenag.go.id/cmsq/source/s01/054019.mp3",
    "surat_id": 54,
    "juz_id": 27,
    "page_number": 529
  },
  {
    "ayat_id": 4866,
    "ayat_number": 20,
    "ayat_arabic": "تَنْزِعُ النَّاسَۙ كَاَنَّهُمْ اَعْجَازُ نَخْلٍ مُّنْقَعِرٍ ",
    "ayat_bahasa": "yang membuat manusia bergelimpangan, mereka bagaikan pohon-pohon kurma yang tumbang dengan akar-akarnya. ",
    "ayat_sound": "https://quran.kemenag.go.id/cmsq/source/s01/054020.mp3",
    "surat_id": 54,
    "juz_id": 27,
    "page_number": 529
  },
  {
    "ayat_id": 4867,
    "ayat_number": 21,
    "ayat_arabic": "فَكَيْفَ كَانَ عَذَابِيْ وَنُذُرِ",
    "ayat_bahasa": "Maka betapa dahsyatnya azab-Ku dan peringatan-Ku! ",
    "ayat_sound": "https://quran.kemenag.go.id/cmsq/source/s01/054021.mp3",
    "surat_id": 54,
    "juz_id": 27,
    "page_number": 529
  },
  {
    "ayat_id": 4868,
    "ayat_number": 22,
    "ayat_arabic": "وَلَقَدْ يَسَّرْنَا الْقُرْاٰنَ لِلذِّكْرِ فَهَلْ مِنْ مُّدَّكِرٍ ࣖ ",
    "ayat_bahasa": "Dan sungguh, telah Kami mudahkan Al-Qur'an untuk peringatan, maka adakah orang yang mau mengambil pelajaran?",
    "ayat_sound": "https://quran.kemenag.go.id/cmsq/source/s01/054022.mp3",
    "surat_id": 54,
    "juz_id": 27,
    "page_number": 529
  },
  {
    "ayat_id": 4869,
    "ayat_number": 23,
    "ayat_arabic": "كَذَّبَتْ ثَمُوْدُ بِالنُّذُرِ",
    "ayat_bahasa": "Kaum Samud pun telah mendustakan peringatan itu.",
    "ayat_sound": "https://quran.kemenag.go.id/cmsq/source/s01/054023.mp3",
    "surat_id": 54,
    "juz_id": 27,
    "page_number": 529
  },
  {
    "ayat_id": 4870,
    "ayat_number": 24,
    "ayat_arabic": "فَقَالُوْٓا اَبَشَرًا مِّنَّا وَاحِدًا نَّتَّبِعُهٗٓ  ۙاِنَّآ اِذًا لَّفِيْ ضَلٰلٍ وَّسُعُرٍ",
    "ayat_bahasa": "Maka mereka berkata, “Bagaimana kita akan mengikuti seorang manusia (biasa) di antara kita? Sungguh, kalau begitu kita benar-benar telah sesat dan gila. ",
    "ayat_sound": "https://quran.kemenag.go.id/cmsq/source/s01/054024.mp3",
    "surat_id": 54,
    "juz_id": 27,
    "page_number": 529
  },
  {
    "ayat_id": 4871,
    "ayat_number": 25,
    "ayat_arabic": "ءَاُلْقِيَ الذِّكْرُ عَلَيْهِ مِنْۢ بَيْنِنَا بَلْ هُوَ كَذَّابٌ اَشِرٌ ",
    "ayat_bahasa": "Apakah wahyu itu diturunkan kepadanya di antara kita? Pastilah dia (Saleh) seorang yang sangat pendusta (dan) sombong.” ",
    "ayat_sound": "https://quran.kemenag.go.id/cmsq/source/s01/054025.mp3",
    "surat_id": 54,
    "juz_id": 27,
    "page_number": 529
  },
  {
    "ayat_id": 4872,
    "ayat_number": 26,
    "ayat_arabic": "سَيَعْلَمُوْنَ غَدًا مَّنِ الْكَذَّابُ الْاَشِرُ ",
    "ayat_bahasa": "Kelak mereka akan mengetahui siapa yang sebenarnya sangat pendusta (dan) sombong itu.",
    "ayat_sound": "https://quran.kemenag.go.id/cmsq/source/s01/054026.mp3",
    "surat_id": 54,
    "juz_id": 27,
    "page_number": 529
  },
  {
    "ayat_id": 4873,
    "ayat_number": 27,
    "ayat_arabic": "اِنَّا مُرْسِلُوا النَّاقَةِ فِتْنَةً لَّهُمْ فَارْتَقِبْهُمْ وَاصْطَبِرْۖ  ",
    "ayat_bahasa": "Sesungguhnya Kami akan mengirimkan unta betina sebagai cobaan bagi mereka, maka tunggulah mereka dan bersabarlah (Saleh).",
    "ayat_sound": "https://quran.kemenag.go.id/cmsq/source/s01/054027.mp3",
    "surat_id": 54,
    "juz_id": 27,
    "page_number": 529
  },
  {
    "ayat_id": 4874,
    "ayat_number": 28,
    "ayat_arabic": "وَنَبِّئْهُمْ اَنَّ الْمَاۤءَ قِسْمَةٌ ۢ بَيْنَهُمْۚ  كُلُّ شِرْبٍ مُّحْتَضَرٌ ",
    "ayat_bahasa": "Dan beritahukanlah kepada mereka bahwa air itu dibagi di antara mereka (dengan unta betina itu); setiap orang berhak mendapat giliran minum.",
    "ayat_sound": "https://quran.kemenag.go.id/cmsq/source/s01/054028.mp3",
    "surat_id": 54,
    "juz_id": 27,
    "page_number": 530
  },
  {
    "ayat_id": 4875,
    "ayat_number": 29,
    "ayat_arabic": "فَنَادَوْا صَاحِبَهُمْ فَتَعَاطٰى فَعَقَرَ ",
    "ayat_bahasa": "Maka mereka memanggil kawannya, lalu dia menangkap (unta itu) dan memotongnya. ",
    "ayat_sound": "https://quran.kemenag.go.id/cmsq/source/s01/054029.mp3",
    "surat_id": 54,
    "juz_id": 27,
    "page_number": 530
  },
  {
    "ayat_id": 4876,
    "ayat_number": 30,
    "ayat_arabic": "فَكَيْفَ كَانَ عَذَابِيْ وَنُذُرِ ",
    "ayat_bahasa": "Maka betapa dahsyatnya azab-Ku dan peringatan-Ku!",
    "ayat_sound": "https://quran.kemenag.go.id/cmsq/source/s01/054030.mp3",
    "surat_id": 54,
    "juz_id": 27,
    "page_number": 530
  },
  {
    "ayat_id": 4877,
    "ayat_number": 31,
    "ayat_arabic": "اِنَّآ اَرْسَلْنَا عَلَيْهِمْ صَيْحَةً وَّاحِدَةً فَكَانُوْا كَهَشِيْمِ الْمُحْتَظِرِ",
    "ayat_bahasa": "Kami kirimkan atas mereka satu suara yang keras mengguntur, maka jadilah mereka seperti batang-batang kering yang lapuk. ",
    "ayat_sound": "https://quran.kemenag.go.id/cmsq/source/s01/054031.mp3",
    "surat_id": 54,
    "juz_id": 27,
    "page_number": 530
  },
  {
    "ayat_id": 4878,
    "ayat_number": 32,
    "ayat_arabic": "وَلَقَدْ يَسَّرْنَا الْقُرْاٰنَ لِلذِّكْرِ فَهَلْ مِنْ مُّدَّكِرٍ ",
    "ayat_bahasa": "Dan sungguh, telah Kami mudahkan Al-Qur'an untuk peringatan, maka adakah orang yang mau mengambil pelajaran?",
    "ayat_sound": "https://quran.kemenag.go.id/cmsq/source/s01/054032.mp3",
    "surat_id": 54,
    "juz_id": 27,
    "page_number": 530
  },
  {
    "ayat_id": 4879,
    "ayat_number": 33,
    "ayat_arabic": "كَذَّبَتْ قَوْمُ لُوْطٍ ۢبِالنُّذُرِ ",
    "ayat_bahasa": "Kaum Lut pun telah mendustakan peringatan itu. ",
    "ayat_sound": "https://quran.kemenag.go.id/cmsq/source/s01/054033.mp3",
    "surat_id": 54,
    "juz_id": 27,
    "page_number": 530
  },
  {
    "ayat_id": 4880,
    "ayat_number": 34,
    "ayat_arabic": "اِنَّآ اَرْسَلْنَا عَلَيْهِمْ حَاصِبًا اِلَّآ اٰلَ لُوْطٍ ۗنَجَّيْنٰهُمْ بِسَحَرٍۙ",
    "ayat_bahasa": "Sesungguhnya Kami kirimkan kepada mereka badai yang membawa batu-batu (yang menimpa mereka), kecuali keluarga Lut. Kami selamatkan mereka sebelum fajar menyingsing,",
    "ayat_sound": "https://quran.kemenag.go.id/cmsq/source/s01/054034.mp3",
    "surat_id": 54,
    "juz_id": 27,
    "page_number": 530
  },
  {
    "ayat_id": 4881,
    "ayat_number": 35,
    "ayat_arabic": "نِّعْمَةً مِّنْ عِنْدِنَاۗ  كَذٰلِكَ نَجْزِيْ مَنْ شَكَرَ ",
    "ayat_bahasa": "sebagai nikmat dari Kami. Demikianlah Kami memberi balasan kepada orang-orang yang bersyukur. ",
    "ayat_sound": "https://quran.kemenag.go.id/cmsq/source/s01/054035.mp3",
    "surat_id": 54,
    "juz_id": 27,
    "page_number": 530
  },
  {
    "ayat_id": 4882,
    "ayat_number": 36,
    "ayat_arabic": "وَلَقَدْ اَنْذَرَهُمْ بَطْشَتَنَا فَتَمَارَوْا بِالنُّذُرِ ",
    "ayat_bahasa": "Dan sungguh, dia (Lut) telah memperingatkan mereka akan hukuman Kami, tetapi mereka mendustakan peringatan-Ku. ",
    "ayat_sound": "https://quran.kemenag.go.id/cmsq/source/s01/054036.mp3",
    "surat_id": 54,
    "juz_id": 27,
    "page_number": 530
  },
  {
    "ayat_id": 4883,
    "ayat_number": 37,
    "ayat_arabic": "وَلَقَدْ رَاوَدُوْهُ عَنْ ضَيْفِهٖ فَطَمَسْنَآ اَعْيُنَهُمْ فَذُوْقُوْا عَذَابِيْ وَنُذُرِ ",
    "ayat_bahasa": "Dan sungguh, mereka telah membujuknya (agar menyerahkan) tamunya (kepada mereka), lalu Kami butakan mata mereka, maka rasakanlah azab-Ku dan peringatan-Ku!",
    "ayat_sound": "https://quran.kemenag.go.id/cmsq/source/s01/054037.mp3",
    "surat_id": 54,
    "juz_id": 27,
    "page_number": 530
  },
  {
    "ayat_id": 4884,
    "ayat_number": 38,
    "ayat_arabic": "وَلَقَدْ صَبَّحَهُمْ بُكْرَةً عَذَابٌ مُّسْتَقِرٌّۚ  ",
    "ayat_bahasa": "Dan sungguh, pada esok harinya mereka benar-benar ditimpa azab yang tetap.",
    "ayat_sound": "https://quran.kemenag.go.id/cmsq/source/s01/054038.mp3",
    "surat_id": 54,
    "juz_id": 27,
    "page_number": 530
  },
  {
    "ayat_id": 4885,
    "ayat_number": 39,
    "ayat_arabic": "فَذُوْقُوْا عَذَابِيْ وَنُذُرِ ",
    "ayat_bahasa": "Maka rasakanlah azab-Ku dan peringatan-Ku!",
    "ayat_sound": "https://quran.kemenag.go.id/cmsq/source/s01/054039.mp3",
    "surat_id": 54,
    "juz_id": 27,
    "page_number": 530
  },
  {
    "ayat_id": 4886,
    "ayat_number": 40,
    "ayat_arabic": "وَلَقَدْ يَسَّرْنَا الْقُرْاٰنَ لِلذِّكْرِ فَهَلْ مِنْ مُّدَّكِرٍ ࣖ",
    "ayat_bahasa": "Dan sungguh, telah Kami mudahkan Al-Qur'an untuk peringatan, maka adakah orang yang mau mengambil pelajaran? ",
    "ayat_sound": "https://quran.kemenag.go.id/cmsq/source/s01/054040.mp3",
    "surat_id": 54,
    "juz_id": 27,
    "page_number": 530
  },
  {
    "ayat_id": 4887,
    "ayat_number": 41,
    "ayat_arabic": "وَلَقَدْ جَاۤءَ اٰلَ فِرْعَوْنَ النُّذُرُۚ  ",
    "ayat_bahasa": "Dan sungguh, peringatan telah datang kepada keluarga Fir‘aun. ",
    "ayat_sound": "https://quran.kemenag.go.id/cmsq/source/s01/054041.mp3",
    "surat_id": 54,
    "juz_id": 27,
    "page_number": 530
  },
  {
    "ayat_id": 4888,
    "ayat_number": 42,
    "ayat_arabic": "كَذَّبُوْا بِاٰيٰتِنَا كُلِّهَا فَاَخَذْنٰهُمْ اَخْذَ عَزِيْزٍ مُّقْتَدِرٍ ",
    "ayat_bahasa": "Mereka mendustakan mukjizat-mukjizat Kami semuanya, maka Kami azab mereka dengan azab dari Yang Mahaperkasa, Mahakuasa.",
    "ayat_sound": "https://quran.kemenag.go.id/cmsq/source/s01/054042.mp3",
    "surat_id": 54,
    "juz_id": 27,
    "page_number": 530
  },
  {
    "ayat_id": 4889,
    "ayat_number": 43,
    "ayat_arabic": "اَكُفَّارُكُمْ خَيْرٌ مِّنْ اُولٰۤىِٕكُمْ اَمْ لَكُمْ بَرَاۤءَةٌ فِى الزُّبُرِۚ",
    "ayat_bahasa": "Apakah orang-orang kafir di lingkunganmu (kaum musyrikin) lebih baik dari mereka, ataukah kamu telah mempunyai jaminan kebebasan (dari azab) dalam kitab-kitab terdahulu? ",
    "ayat_sound": "https://quran.kemenag.go.id/cmsq/source/s01/054043.mp3",
    "surat_id": 54,
    "juz_id": 27,
    "page_number": 530
  },
  {
    "ayat_id": 4890,
    "ayat_number": 44,
    "ayat_arabic": "اَمْ يَقُوْلُوْنَ نَحْنُ جَمِيْعٌ مُّنْتَصِرٌ ",
    "ayat_bahasa": "Atau mereka mengatakan, “Kami ini golongan yang bersatu yang pasti menang.” ",
    "ayat_sound": "https://quran.kemenag.go.id/cmsq/source/s01/054044.mp3",
    "surat_id": 54,
    "juz_id": 27,
    "page_number": 530
  },
  {
    "ayat_id": 4891,
    "ayat_number": 45,
    "ayat_arabic": "سَيُهْزَمُ الْجَمْعُ وَيُوَلُّوْنَ الدُّبُرَ",
    "ayat_bahasa": "Golongan itu pasti akan dikalahkan dan mereka akan mundur ke belakang. ",
    "ayat_sound": "https://quran.kemenag.go.id/cmsq/source/s01/054045.mp3",
    "surat_id": 54,
    "juz_id": 27,
    "page_number": 530
  },
  {
    "ayat_id": 4892,
    "ayat_number": 46,
    "ayat_arabic": "بَلِ السَّاعَةُ مَوْعِدُهُمْ وَالسَّاعَةُ اَدْهٰى وَاَمَرُّ ",
    "ayat_bahasa": "Bahkan hari Kiamat itulah hari yang dijanjikan kepada mereka dan hari Kiamat itu lebih dahsyat dan lebih pahit. ",
    "ayat_sound": "https://quran.kemenag.go.id/cmsq/source/s01/054046.mp3",
    "surat_id": 54,
    "juz_id": 27,
    "page_number": 530
  },
  {
    "ayat_id": 4893,
    "ayat_number": 47,
    "ayat_arabic": "اِنَّ الْمُجْرِمِيْنَ فِيْ ضَلٰلٍ وَّسُعُرٍۘ ",
    "ayat_bahasa": "Sungguh, orang-orang yang berdosa berada dalam kesesatan (di dunia) dan akan berada dalam neraka (di akhirat). ",
    "ayat_sound": "https://quran.kemenag.go.id/cmsq/source/s01/054047.mp3",
    "surat_id": 54,
    "juz_id": 27,
    "page_number": 530
  },
  {
    "ayat_id": 4894,
    "ayat_number": 48,
    "ayat_arabic": "يَوْمَ يُسْحَبُوْنَ فِى النَّارِ عَلٰى وُجُوْهِهِمْۗ ذُوْقُوْا مَسَّ سَقَرَ",
    "ayat_bahasa": "Pada hari mereka diseret ke neraka pada wajahnya. (Dikatakan kepada mereka), “Rasakanlah sentuhan api neraka.”",
    "ayat_sound": "https://quran.kemenag.go.id/cmsq/source/s01/054048.mp3",
    "surat_id": 54,
    "juz_id": 27,
    "page_number": 530
  },
  {
    "ayat_id": 4895,
    "ayat_number": 49,
    "ayat_arabic": "اِنَّا كُلَّ شَيْءٍ خَلَقْنٰهُ بِقَدَرٍ ",
    "ayat_bahasa": "Sungguh, Kami menciptakan segala sesuatu menurut ukuran. ",
    "ayat_sound": "https://quran.kemenag.go.id/cmsq/source/s01/054049.mp3",
    "surat_id": 54,
    "juz_id": 27,
    "page_number": 530
  },
  {
    "ayat_id": 4896,
    "ayat_number": 50,
    "ayat_arabic": "وَمَآ اَمْرُنَآ اِلَّا وَاحِدَةٌ كَلَمْحٍ ۢبِالْبَصَرِ ",
    "ayat_bahasa": "Dan perintah Kami hanyalah (dengan) satu perkataan seperti kejapan mata. ",
    "ayat_sound": "https://quran.kemenag.go.id/cmsq/source/s01/054050.mp3",
    "surat_id": 54,
    "juz_id": 27,
    "page_number": 531
  },
  {
    "ayat_id": 4897,
    "ayat_number": 51,
    "ayat_arabic": "وَلَقَدْ اَهْلَكْنَآ اَشْيَاعَكُمْ فَهَلْ مِنْ مُّدَّكِرٍ ",
    "ayat_bahasa": "Dan sungguh, telah Kami binasakan orang yang serupa dengan kamu (kekafirannya). Maka adakah orang yang mau mengambil pelajaran?",
    "ayat_sound": "https://quran.kemenag.go.id/cmsq/source/s01/054051.mp3",
    "surat_id": 54,
    "juz_id": 27,
    "page_number": 531
  },
  {
    "ayat_id": 4898,
    "ayat_number": 52,
    "ayat_arabic": "وَكُلُّ شَيْءٍ فَعَلُوْهُ فِى الزُّبُرِ ",
    "ayat_bahasa": "Dan segala sesuatu yang telah mereka perbuat tercatat dalam buku-buku catatan.",
    "ayat_sound": "https://quran.kemenag.go.id/cmsq/source/s01/054052.mp3",
    "surat_id": 54,
    "juz_id": 27,
    "page_number": 531
  },
  {
    "ayat_id": 4899,
    "ayat_number": 53,
    "ayat_arabic": "وَكُلُّ صَغِيْرٍ وَّكَبِيْرٍ مُّسْتَطَرٌ ",
    "ayat_bahasa": "Dan segala (sesuatu) yang kecil maupun yang besar (semuanya) tertulis. ",
    "ayat_sound": "https://quran.kemenag.go.id/cmsq/source/s01/054053.mp3",
    "surat_id": 54,
    "juz_id": 27,
    "page_number": 531
  },
  {
    "ayat_id": 4900,
    "ayat_number": 54,
    "ayat_arabic": "اِنَّ الْمُتَّقِيْنَ فِيْ جَنّٰتٍ وَّنَهَرٍۙ  ",
    "ayat_bahasa": "Sungguh, orang-orang yang bertakwa berada di taman-taman dan sungai-sungai,",
    "ayat_sound": "https://quran.kemenag.go.id/cmsq/source/s01/054054.mp3",
    "surat_id": 54,
    "juz_id": 27,
    "page_number": 531
  },
  {
    "ayat_id": 4901,
    "ayat_number": 55,
    "ayat_arabic": "فِيْ مَقْعَدِ صِدْقٍ عِنْدَ مَلِيْكٍ مُّقْتَدِرٍ ࣖ ",
    "ayat_bahasa": "di tempat yang disenangi di sisi Tuhan Yang Mahakuasa.",
    "ayat_sound": "https://quran.kemenag.go.id/cmsq/source/s01/054055.mp3",
    "surat_id": 54,
    "juz_id": 27,
    "page_number": 531
  }
]